cecdaemon/__init__.py
cecdaemon/__main__.py
cecdaemon/cecdaemon.py
cecdaemon/cecusercodes.py
cecdaemon/const.py
cecdaemon/custom_cmd.py
cecdaemon/remote.py
cecdaemon/trigger.py
cecdaemon/tv.py
cecdaemon-1.0.0.dist-info/METADATA
cecdaemon-1.0.0.dist-info/RECORD
cecdaemon-1.0.0.dist-info/WHEEL
cecdaemon-1.0.0.dist-info/entry_points.txt
cecdaemon-1.0.0.dist-info/top_level.txt
usr/share/cecdaemon/cecdaemon.conf-example
usr/share/cecdaemon/cecdaemon.service-example
usr/share/cecdaemon/example_server.py
