Metadata-Version: 2.1
Name: cecdaemon
Version: 1.0.0
Summary: Daemon and tools for managing CEC capabilities
Home-page: https://github.com/simons-public/cecdaemon
Author: Chris Simons
Author-email: chris@simonsmail.net
License: UNKNOWN
Keywords: libcec cec daemon htpc
Platform: UNKNOWN
Classifier: Development Status :: 3 - Alpha
Classifier: Environment :: No Input/Output (Daemon)
Classifier: Topic :: Games/Entertainment
Classifier: Operating System :: POSIX :: Linux
Classifier: Programming Language :: Python :: 3.6
Classifier: License :: OSI Approved :: BSD License
Requires-Dist: cec
Requires-Dist: python-uinput
